{"commitInfo":{"timestamp":1731534251742,"userId":"819115780627724","userName":"yus_bibi_data@outlook.com","operation":"CREATE OR REPLACE TABLE AS SELECT","operationParameters":{"isManaged":"true","description":null,"partitionBy":"[\"customer_id\"]","properties":"{}"},"notebook":{"notebookId":"3398856716476721"},"clusterId":"1112-155628-asltcbxm","isolationLevel":"WriteSerializable","isBlindAppend":false,"operationMetrics":{"numFiles":"2","numOutputRows":"2","numOutputBytes":"2987"},"engineInfo":"Databricks-Runtime/11.3.x-scala2.12","txnId":"59502067-d012-4e97-8480-c508e5b9a8b1"}}
{"protocol":{"minReaderVersion":1,"minWriterVersion":2}}
{"metaData":{"id":"62f1dd68-ecae-4891-b989-f5b18e8edea8","format":{"provider":"parquet","options":{}},"schemaString":"{\"type\":\"struct\",\"fields\":[{\"name\":\"customer_id\",\"type\":\"string\",\"nullable\":true,\"metadata\":{}},{\"name\":\"transaction_date\",\"type\":\"date\",\"nullable\":true,\"metadata\":{}},{\"name\":\"DiscountAmount\",\"type\":\"double\",\"nullable\":true,\"metadata\":{}},{\"name\":\"file_date\",\"type\":\"string\",\"nullable\":true,\"metadata\":{}},{\"name\":\"ingestion_date\",\"type\":\"timestamp\",\"nullable\":true,\"metadata\":{}}]}","partitionColumns":["customer_id"],"configuration":{},"createdTime":1731534250818}}
{"add":{"path":"customer_id=CUST001/part-00000-ff68d06b-7a99-4bf1-98bb-2477071683a7.c000.snappy.parquet","partitionValues":{"customer_id":"CUST001"},"size":1493,"modificationTime":1731534251000,"dataChange":true,"stats":"{\"numRecords\":1,\"minValues\":{\"transaction_date\":\"2023-06-18\",\"DiscountAmount\":3.69,\"file_date\":\"2024-11-01\",\"ingestion_date\":\"2024-11-13T21:44:10.679Z\"},\"maxValues\":{\"transaction_date\":\"2023-06-18\",\"DiscountAmount\":3.69,\"file_date\":\"2024-11-01\",\"ingestion_date\":\"2024-11-13T21:44:10.679Z\"},\"nullCount\":{\"transaction_date\":0,\"DiscountAmount\":0,\"file_date\":0,\"ingestion_date\":0}}","tags":{"INSERTION_TIME":"1731534251000000","MIN_INSERTION_TIME":"1731534251000000","MAX_INSERTION_TIME":"1731534251000000","OPTIMIZE_TARGET_SIZE":"268435456"}}}
{"add":{"path":"customer_id=CUST002/part-00000-f8e33c76-0f72-48ad-b38c-69f76231b4c8.c000.snappy.parquet","partitionValues":{"customer_id":"CUST002"},"size":1494,"modificationTime":1731534251000,"dataChange":true,"stats":"{\"numRecords\":1,\"minValues\":{\"transaction_date\":\"2023-01-05\",\"DiscountAmount\":1.62,\"file_date\":\"2024-11-01\",\"ingestion_date\":\"2024-11-13T21:44:10.679Z\"},\"maxValues\":{\"transaction_date\":\"2023-01-05\",\"DiscountAmount\":1.62,\"file_date\":\"2024-11-01\",\"ingestion_date\":\"2024-11-13T21:44:10.679Z\"},\"nullCount\":{\"transaction_date\":0,\"DiscountAmount\":0,\"file_date\":0,\"ingestion_date\":0}}","tags":{"INSERTION_TIME":"1731534251000001","MIN_INSERTION_TIME":"1731534251000001","MAX_INSERTION_TIME":"1731534251000001","OPTIMIZE_TARGET_SIZE":"268435456"}}}
