{"commitInfo":{"timestamp":1731544506481,"userId":"7487267338633875","userName":"ed82c781-b84c-48fa-a7ee-f25d1910ed2a","operation":"MERGE","operationParameters":{"predicate":"[\"(customer_id#3409 = customer_id#3350)\"]","matchedPredicates":"[{\"actionType\":\"update\"}]","notMatchedPredicates":"[{\"actionType\":\"insert\"}]"},"job":{"jobId":"999202091825554","jobName":"ADF_clv-adf_ingest_customer_info_pl_ingest_discounts_data_2e37d2bc-ee39-44a4-a912-3780f85eec99","runId":"444508549876863","jobOwnerId":"7487267338633875","triggerType":"manual"},"notebook":{"notebookId":"3398856716476721"},"clusterId":"1112-155628-asltcbxm","readVersion":2,"isolationLevel":"WriteSerializable","isBlindAppend":false,"operationMetrics":{"numTargetRowsCopied":"0","numTargetRowsDeleted":"0","numTargetFilesAdded":"2","executionTimeMs":"5501","materializeSourceTimeMs":"161","numTargetRowsInserted":"0","scanTimeMs":"2503","numTargetRowsUpdated":"2","numOutputRows":"2","numTargetChangeFilesAdded":"0","numSourceRows":"2","numTargetFilesRemoved":"2","rewriteTimeMs":"1349"},"engineInfo":"Databricks-Runtime/11.3.x-scala2.12","txnId":"647ea8ba-b987-4c6c-8ac2-3ca33ffc296e"}}
{"remove":{"path":"customer_id=CUST002/part-00000-f8e33c76-0f72-48ad-b38c-69f76231b4c8.c000.snappy.parquet","deletionTimestamp":1731544506393,"dataChange":true,"extendedFileMetadata":true,"partitionValues":{"customer_id":"CUST002"},"size":1494,"tags":{"INSERTION_TIME":"1731534251000001","MIN_INSERTION_TIME":"1731534251000001","MAX_INSERTION_TIME":"1731534251000001","OPTIMIZE_TARGET_SIZE":"268435456"}}}
{"remove":{"path":"customer_id=CUST001/part-00000-ff68d06b-7a99-4bf1-98bb-2477071683a7.c000.snappy.parquet","deletionTimestamp":1731544506393,"dataChange":true,"extendedFileMetadata":true,"partitionValues":{"customer_id":"CUST001"},"size":1493,"tags":{"INSERTION_TIME":"1731534251000000","MIN_INSERTION_TIME":"1731534251000000","MAX_INSERTION_TIME":"1731534251000000","OPTIMIZE_TARGET_SIZE":"268435456"}}}
{"add":{"path":"customer_id=CUST001/part-00000-41adf5b2-890d-4905-b578-0079a3511159.c000.snappy.parquet","partitionValues":{"customer_id":"CUST001"},"size":1493,"modificationTime":1731544506000,"dataChange":true,"stats":"{\"numRecords\":1,\"minValues\":{\"transaction_date\":\"2023-06-18\",\"DiscountAmount\":3.69,\"file_date\":\"2024-11-01\",\"ingestion_date\":\"2024-11-14T00:35:00.957Z\"},\"maxValues\":{\"transaction_date\":\"2023-06-18\",\"DiscountAmount\":3.69,\"file_date\":\"2024-11-01\",\"ingestion_date\":\"2024-11-14T00:35:00.957Z\"},\"nullCount\":{\"transaction_date\":0,\"DiscountAmount\":0,\"file_date\":0,\"ingestion_date\":0}}","tags":{"INSERTION_TIME":"1731544506000000","MIN_INSERTION_TIME":"1731534251000000","MAX_INSERTION_TIME":"1731544506000000","OPTIMIZE_TARGET_SIZE":"268435456"}}}
{"add":{"path":"customer_id=CUST002/part-00000-5cd66e9b-5639-4126-a315-103241c7a891.c000.snappy.parquet","partitionValues":{"customer_id":"CUST002"},"size":1494,"modificationTime":1731544506000,"dataChange":true,"stats":"{\"numRecords\":1,\"minValues\":{\"transaction_date\":\"2023-01-05\",\"DiscountAmount\":1.62,\"file_date\":\"2024-11-01\",\"ingestion_date\":\"2024-11-14T00:35:00.957Z\"},\"maxValues\":{\"transaction_date\":\"2023-01-05\",\"DiscountAmount\":1.62,\"file_date\":\"2024-11-01\",\"ingestion_date\":\"2024-11-14T00:35:00.957Z\"},\"nullCount\":{\"transaction_date\":0,\"DiscountAmount\":0,\"file_date\":0,\"ingestion_date\":0}}","tags":{"INSERTION_TIME":"1731544506000001","MIN_INSERTION_TIME":"1731534251000000","MAX_INSERTION_TIME":"1731544506000001","OPTIMIZE_TARGET_SIZE":"268435456"}}}
